{
  "opensearch_parameters_version": 1,
  "about": "These are the default CKAN OpenSearch parameters",
  "about_url": "http://github.com/nextgeoss/ckanext-opensearch#parameters",
  "collection_params_list": [
    {
        "name": "Sentinel-1 Level-1 (SLC)",
        "id": "SENTINEL1_L1_SLC",
        "file": "SENTINEL1_L1_SLC"
    },
    {
        "name": "Sentinel-1 Level-1 (GRD)",
        "id": "SENTINEL1_L1_GRD",
        "file": "SENTINEL1_L1_GRD"
    },
    {
        "name": "Sentinel-1 Level-2 (OCN)",
        "id": "SENTINEL1_L2_OCN",
        "file": "SENTINEL1_L2_OCN"
    },
    {
        "name": "Sentinel-2 Level-1C",
        "id": "SENTINEL2_L1C",
        "file": "SENTINEL2_L1C"
    },
    {
        "name": "Sentinel-2 Level-2A",
        "id": "SENTINEL2_L2A",
        "file": "SENTINEL2_L2A"
    },
    {
        "name": "Sentinel-3 SRAL Level-1 Calibration",
        "id": "SENTINEL3_SRAL_L1_CAL",
        "file": "SENTINEL3_SRAL_L1_CAL"
    },
    {
        "name": "Sentinel-3 SRAL Level-1 SRA",
        "id": "SENTINEL3_SRAL_L1_SRA",
        "file": "SENTINEL3_SRAL_L1_SRA"
    },
    {
        "name": "Sentinel-3 SRAL Level-2 Land",
        "id": "SENTINEL3_SRAL_L2_LAN",
        "file": "SENTINEL3_SRAL_L2_LAN"
    },
    {
        "name": "Sentinel-3 SRAL Level-2 Water",
        "id": "SENTINEL3_SRAL_L2_WAT",
        "file": "SENTINEL3_SRAL_L2_WAT"
    }
  ]
}